{"created_at": "Mon Aug 03 13:07:33 +0000 2015", "id": 628190466438135808, "id_str": "628190466438135808", "text": "5/ presidential primary, Newt Gingrich\u2019s campaign ran an ad in South Carolina attacking Mitt Romney for being proficient in French.In", "truncated": false, "entities": {"hashtags": [], "symbols": [], "user_mentions": [], "urls": []}, "source": "<a href=\"https://280.talltweets.com/\" rel=\"nofollow\">Tall Tweets</a>", "in_reply_to_status_id": 628190457193869312, "in_reply_to_status_id_str": "628190457193869312", "in_reply_to_user_id": 42083927, "in_reply_to_user_id_str": "42083927", "in_reply_to_screen_name": "JaviersonMcCoy", "user": {"id": 42083927, "id_str": "42083927", "name": "Javierson McCoy", "screen_name": "JaviersonMcCoy", "location": "Orlando, Florida", "description": "We are not everything you see because this should not be considered seeing all that we are. All my tweets are solely based on my opinion.", "url": null, "entities": {"description": {"urls": []}}, "protected": false, "followers_count": 482, "friends_count": 2174, "listed_count": 6, "created_at": "Sat May 23 19:36:28 +0000 2009", "favourites_count": 3951, "utc_offset": null, "time_zone": null, "geo_enabled": true, "verified": false, "statuses_count": 16946, "lang": null, "contributors_enabled": false, "is_translator": false, "is_translation_enabled": false, "profile_background_color": "8B542B", "profile_background_image_url": "http://abs.twimg.com/images/themes/theme8/bg.gif", "profile_background_image_url_https": "https://abs.twimg.com/images/themes/theme8/bg.gif", "profile_background_tile": false, "profile_image_url": "http://pbs.twimg.com/profile_images/974021079751712769/h908SoR__normal.jpg", "profile_image_url_https": "https://pbs.twimg.com/profile_images/974021079751712769/h908SoR__normal.jpg", "profile_banner_url": "https://pbs.twimg.com/profile_banners/42083927/1521060046", "profile_link_color": "9D582E", "profile_sidebar_border_color": "D9B17E", "profile_sidebar_fill_color": "EADEAA", "profile_text_color": "333333", "profile_use_background_image": true, "has_extended_profile": true, "default_profile": false, "default_profile_image": false, "following": null, "follow_request_sent": null, "notifications": null, "translator_type": "none", "withheld_in_countries": []}, "geo": null, "coordinates": null, "place": null, "contributors": null, "is_quote_status": false, "retweet_count": 0, "favorite_count": 0, "favorited": false, "retweeted": false, "lang": "en"}