{"created_at": "Wed Jun 27 08:11:02 +0000 2018", "id": 1011884597678927872, "id_str": "1011884597678927872", "text": "Do I truly want a nation that works or I want a nation that works with me as the leader &amp; the face of that movement?", "truncated": false, "entities": {"hashtags": [], "symbols": [], "user_mentions": [], "urls": []}, "source": "<a href=\"http://www.facebook.com/twitter\" rel=\"nofollow\">Facebook</a>", "in_reply_to_status_id": null, "in_reply_to_status_id_str": null, "in_reply_to_user_id": null, "in_reply_to_user_id_str": null, "in_reply_to_screen_name": null, "user": {"id": 192859276, "id_str": "192859276", "name": "thefamilylifestrategist", "screen_name": "praisefowowe", "location": "Dallas Texas ", "description": "Husband, Father, Man & Global Family Life Innovator & Strategist", "url": "https://t.co/6Xhh93ZONi", "entities": {"url": {"urls": [{"url": "https://t.co/6Xhh93ZONi", "expanded_url": "http://www.iampraisefowowe.com", "display_url": "iampraisefowowe.com", "indices": [0, 23]}]}, "description": {"urls": []}}, "protected": false, "followers_count": 29360, "friends_count": 1684, "listed_count": 121, "created_at": "Mon Sep 20 10:40:49 +0000 2010", "favourites_count": 197, "utc_offset": null, "time_zone": null, "geo_enabled": true, "verified": false, "statuses_count": 95763, "lang": null, "contributors_enabled": false, "is_translator": false, "is_translation_enabled": false, "profile_background_color": "EBEBEB", "profile_background_image_url": "http://abs.twimg.com/images/themes/theme1/bg.png", "profile_background_image_url_https": "https://abs.twimg.com/images/themes/theme1/bg.png", "profile_background_tile": true, "profile_image_url": "http://pbs.twimg.com/profile_images/1003960708353134592/dnEfVPP__normal.jpg", "profile_image_url_https": "https://pbs.twimg.com/profile_images/1003960708353134592/dnEfVPP__normal.jpg", "profile_banner_url": "https://pbs.twimg.com/profile_banners/192859276/1639011687", "profile_link_color": "990000", "profile_sidebar_border_color": "FFFFFF", "profile_sidebar_fill_color": "DDEEF6", "profile_text_color": "333333", "profile_use_background_image": true, "has_extended_profile": false, "default_profile": false, "default_profile_image": false, "following": null, "follow_request_sent": null, "notifications": null, "translator_type": "none", "withheld_in_countries": []}, "geo": null, "coordinates": null, "place": null, "contributors": null, "is_quote_status": false, "retweet_count": 0, "favorite_count": 6, "favorited": false, "retweeted": false, "lang": "en"}