{"created_at": "Wed Oct 17 07:29:28 +0000 2018", "id": 1052461576853315584, "id_str": "1052461576853315584", "text": "https://t.co/Vvm9du4yOP\n27 minutes of the perfect interview w/transcript\nIf you support Drumpf after this, please d\u2026 https://t.co/6yOPZaHbE7", "truncated": true, "entities": {"hashtags": [], "symbols": [], "user_mentions": [], "urls": [{"url": "https://t.co/Vvm9du4yOP", "expanded_url": "https://www.cbsnews.com/news/donald-trump-full-interview-60-minutes-transcript-lesley-stahl-2018-10-14/", "display_url": "cbsnews.com/news/donald-tr\u2026", "indices": [0, 23]}, {"url": "https://t.co/6yOPZaHbE7", "expanded_url": "https://twitter.com/i/web/status/1052461576853315584", "display_url": "twitter.com/i/web/status/1\u2026", "indices": [117, 140]}]}, "source": "<a href=\"http://twitter.com\" rel=\"nofollow\">Twitter Web Client</a>", "in_reply_to_status_id": null, "in_reply_to_status_id_str": null, "in_reply_to_user_id": null, "in_reply_to_user_id_str": null, "in_reply_to_screen_name": null, "user": {"id": 284291761, "id_str": "284291761", "name": "emma darcy", "screen_name": "emmydarcy88", "location": "Left coast", "description": "Out of love, no regrets though the goodness be wasted forever Out of love, no regrets though the return be never Langston Hughes @hopeausten1 alt acct #FBR", "url": null, "entities": {"description": {"urls": []}}, "protected": false, "followers_count": 18430, "friends_count": 18492, "listed_count": 5, "created_at": "Tue Apr 19 01:02:44 +0000 2011", "favourites_count": 135718, "utc_offset": null, "time_zone": null, "geo_enabled": true, "verified": false, "statuses_count": 82698, "lang": null, "contributors_enabled": false, "is_translator": false, "is_translation_enabled": false, "profile_background_color": "0099B9", "profile_background_image_url": "http://abs.twimg.com/images/themes/theme4/bg.gif", "profile_background_image_url_https": "https://abs.twimg.com/images/themes/theme4/bg.gif", "profile_background_tile": false, "profile_image_url": "http://pbs.twimg.com/profile_images/965959325867950081/7vG8i-sS_normal.jpg", "profile_image_url_https": "https://pbs.twimg.com/profile_images/965959325867950081/7vG8i-sS_normal.jpg", "profile_banner_url": "https://pbs.twimg.com/profile_banners/284291761/1413373907", "profile_link_color": "0099B9", "profile_sidebar_border_color": "5ED4DC", "profile_sidebar_fill_color": "95E8EC", "profile_text_color": "3C3940", "profile_use_background_image": true, "has_extended_profile": false, "default_profile": false, "default_profile_image": false, "following": null, "follow_request_sent": null, "notifications": null, "translator_type": "none", "withheld_in_countries": []}, "geo": null, "coordinates": null, "place": null, "contributors": null, "is_quote_status": false, "retweet_count": 0, "favorite_count": 2, "favorited": false, "retweeted": false, "possibly_sensitive": false, "lang": "en"}