{"created_at": "Fri Mar 09 02:37:28 +0000 2018", "id": 971937985389350912, "id_str": "971937985389350912", "text": "[Seattle Police Begin Gun Confiscations: No Laws Broken, No Warrant, No Charges | Zero Hedge] \n https://t.co/NsOfJ4xxJs", "truncated": false, "entities": {"hashtags": [], "symbols": [], "user_mentions": [], "urls": [{"url": "https://t.co/NsOfJ4xxJs", "expanded_url": "https://www.zerohedge.com/news/2018-03-06/seattle-police-begin-gun-confiscations-no-laws-broken-no-warrant-no-charges", "display_url": "zerohedge.com/news/2018-03-0\u2026", "indices": [96, 119]}]}, "source": "<a href=\"http://twitter.com/download/android\" rel=\"nofollow\">Twitter for Android</a>", "in_reply_to_status_id": null, "in_reply_to_status_id_str": null, "in_reply_to_user_id": null, "in_reply_to_user_id_str": null, "in_reply_to_screen_name": null, "user": {"id": 69078882, "id_str": "69078882", "name": "Christene", "screen_name": "Christene101", "location": "United States", "description": "GOD is, Alpha and Omega.#Jew#Christian#Israel \n#Zionist,#America#Federalist\nJohn 7:24 \nPsalms 33:12\nhttps://t.co/XMYSq03LRv. \n\nJan6-awake \n\nGab\n@Christene101", "url": null, "entities": {"description": {"urls": [{"url": "https://t.co/XMYSq03LRv", "expanded_url": "http://pamelageller.com", "display_url": "pamelageller.com", "indices": [100, 123]}]}}, "protected": false, "followers_count": 4018, "friends_count": 4191, "listed_count": 50, "created_at": "Wed Aug 26 20:00:02 +0000 2009", "favourites_count": 26982, "utc_offset": null, "time_zone": null, "geo_enabled": false, "verified": false, "statuses_count": 72061, "lang": null, "contributors_enabled": false, "is_translator": false, "is_translation_enabled": false, "profile_background_color": "1A1B1F", "profile_background_image_url": "http://abs.twimg.com/images/themes/theme9/bg.gif", "profile_background_image_url_https": "https://abs.twimg.com/images/themes/theme9/bg.gif", "profile_background_tile": false, "profile_image_url": "http://pbs.twimg.com/profile_images/1360137143646097408/w27vzUDQ_normal.jpg", "profile_image_url_https": "https://pbs.twimg.com/profile_images/1360137143646097408/w27vzUDQ_normal.jpg", "profile_banner_url": "https://pbs.twimg.com/profile_banners/69078882/1591076238", "profile_link_color": "2FC2EF", "profile_sidebar_border_color": "181A1E", "profile_sidebar_fill_color": "252429", "profile_text_color": "666666", "profile_use_background_image": true, "has_extended_profile": false, "default_profile": false, "default_profile_image": false, "following": null, "follow_request_sent": null, "notifications": null, "translator_type": "none", "withheld_in_countries": []}, "geo": null, "coordinates": null, "place": null, "contributors": null, "is_quote_status": false, "retweet_count": 0, "favorite_count": 0, "favorited": false, "retweeted": false, "possibly_sensitive": false, "lang": "en"}