{"created_at": "Sat Jun 02 20:51:22 +0000 2018", "id": 1003016243920506881, "id_str": "1003016243920506881", "text": "So, let's talk: at the beginning of this video, Adria (the character who's most 'right' in the debate, if a little\u2026 https://t.co/MeRz3uPazW", "truncated": true, "entities": {"hashtags": [], "symbols": [], "user_mentions": [], "urls": [{"url": "https://t.co/MeRz3uPazW", "expanded_url": "https://twitter.com/i/web/status/1003016243920506881", "display_url": "twitter.com/i/web/status/1\u2026", "indices": [116, 139]}]}, "source": "<a href=\"http://twitter.com/download/android\" rel=\"nofollow\">Twitter for Android</a>", "in_reply_to_status_id": null, "in_reply_to_status_id_str": null, "in_reply_to_user_id": null, "in_reply_to_user_id_str": null, "in_reply_to_screen_name": null, "user": {"id": 788964541677711360, "id_str": "788964541677711360", "name": "for the hope of it all \ud83d\udcab", "screen_name": "blusocket", "location": "Level Up - Vienna Teng", "description": "Personal acct for @femfujo1094; 20+, gay, tired, political; reluctantly obsessed with Taylor Swift", "url": "https://t.co/reBQLP0pxS", "entities": {"url": {"urls": [{"url": "https://t.co/reBQLP0pxS", "expanded_url": "http://bit.ly/1OmKw4j", "display_url": "bit.ly/1OmKw4j", "indices": [0, 23]}]}, "description": {"urls": []}}, "protected": false, "followers_count": 57, "friends_count": 185, "listed_count": 3, "created_at": "Thu Oct 20 04:46:19 +0000 2016", "favourites_count": 10544, "utc_offset": null, "time_zone": null, "geo_enabled": false, "verified": false, "statuses_count": 4550, "lang": null, "contributors_enabled": false, "is_translator": false, "is_translation_enabled": false, "profile_background_color": "F5F8FA", "profile_background_image_url": null, "profile_background_image_url_https": null, "profile_background_tile": false, "profile_image_url": "http://pbs.twimg.com/profile_images/1319527420890808321/noMlBXWT_normal.jpg", "profile_image_url_https": "https://pbs.twimg.com/profile_images/1319527420890808321/noMlBXWT_normal.jpg", "profile_banner_url": "https://pbs.twimg.com/profile_banners/788964541677711360/1502789256", "profile_link_color": "1DA1F2", "profile_sidebar_border_color": "C0DEED", "profile_sidebar_fill_color": "DDEEF6", "profile_text_color": "333333", "profile_use_background_image": true, "has_extended_profile": false, "default_profile": true, "default_profile_image": false, "following": null, "follow_request_sent": null, "notifications": null, "translator_type": "none", "withheld_in_countries": []}, "geo": null, "coordinates": null, "place": null, "contributors": null, "is_quote_status": true, "retweet_count": 0, "favorite_count": 0, "favorited": false, "retweeted": false, "possibly_sensitive": false, "lang": "en"}