{"created_at": "Fri Nov 23 15:48:17 +0000 2018", "id": 1065995460136116225, "id_str": "1065995460136116225", "text": "#NAHTPrimary\n\nGreat speech by @andymellor64 @nahtnews summarising the challenges we face whilst encouraging members\u2026 https://t.co/nCexDlMCJA", "truncated": true, "entities": {"hashtags": [{"text": "NAHTPrimary", "indices": [0, 12]}], "symbols": [], "user_mentions": [{"screen_name": "andymellor64", "name": "Andy Mellor", "id": 51557846, "id_str": "51557846", "indices": [30, 43]}, {"screen_name": "NAHTnews", "name": "NAHT", "id": 426558941, "id_str": "426558941", "indices": [44, 53]}], "urls": [{"url": "https://t.co/nCexDlMCJA", "expanded_url": "https://twitter.com/i/web/status/1065995460136116225", "display_url": "twitter.com/i/web/status/1\u2026", "indices": [117, 140]}]}, "source": "<a href=\"http://twitter.com/download/android\" rel=\"nofollow\">Twitter for Android</a>", "in_reply_to_status_id": null, "in_reply_to_status_id_str": null, "in_reply_to_user_id": null, "in_reply_to_user_id_str": null, "in_reply_to_screen_name": null, "user": {"id": 725598249613164544, "id_str": "725598249613164544", "name": "\ud83c\udde8\u200chris \ud83c\uddf0\u200cirkham-\ud83c\uddf0\u200cnowles", "screen_name": "csk240701", "location": "", "description": "#luckyman husband, dad and step-dad.  \nAt work, a happy Primary Executive Lead. I try to represent school leaders on NAHT National Exec.\nAll views my own.", "url": null, "entities": {"description": {"urls": []}}, "protected": false, "followers_count": 669, "friends_count": 935, "listed_count": 4, "created_at": "Thu Apr 28 08:11:18 +0000 2016", "favourites_count": 6127, "utc_offset": null, "time_zone": null, "geo_enabled": true, "verified": false, "statuses_count": 4680, "lang": null, "contributors_enabled": false, "is_translator": false, "is_translation_enabled": false, "profile_background_color": "F5F8FA", "profile_background_image_url": null, "profile_background_image_url_https": null, "profile_background_tile": false, "profile_image_url": "http://pbs.twimg.com/profile_images/1556542295045980161/tck23zmQ_normal.jpg", "profile_image_url_https": "https://pbs.twimg.com/profile_images/1556542295045980161/tck23zmQ_normal.jpg", "profile_banner_url": "https://pbs.twimg.com/profile_banners/725598249613164544/1622181644", "profile_link_color": "1DA1F2", "profile_sidebar_border_color": "C0DEED", "profile_sidebar_fill_color": "DDEEF6", "profile_text_color": "333333", "profile_use_background_image": true, "has_extended_profile": false, "default_profile": true, "default_profile_image": false, "following": null, "follow_request_sent": null, "notifications": null, "translator_type": "none", "withheld_in_countries": []}, "geo": null, "coordinates": null, "place": null, "contributors": null, "is_quote_status": false, "retweet_count": 5, "favorite_count": 12, "favorited": false, "retweeted": false, "lang": "en"}