{"created_at": "Fri Nov 25 20:55:34 +0000 2016", "id": 802254425859309569, "id_str": "802254425859309569", "text": "Inside a Fake News Sausage Factory: \u2018This Is All About Income\u2019 https://t.co/TGWSKmTYJt", "truncated": false, "entities": {"hashtags": [], "symbols": [], "user_mentions": [], "urls": [{"url": "https://t.co/TGWSKmTYJt", "expanded_url": "http://dlvr.it/MlD9YK", "display_url": "dlvr.it/MlD9YK", "indices": [63, 86]}]}, "source": "<a href=\"https://dlvrit.com/\" rel=\"nofollow\">dlvr.it</a>", "in_reply_to_status_id": null, "in_reply_to_status_id_str": null, "in_reply_to_user_id": null, "in_reply_to_user_id_str": null, "in_reply_to_screen_name": null, "user": {"id": 2393490350, "id_str": "2393490350", "name": "MaicOl More\u00e1ux\u2122", "screen_name": "EnanoO_4G", "location": "\u2198C\u03c5\u0454\u0438\u0442\u03b1 \u03d1\u0192\u0192\u026ac\u026a\u03b1I\u2196", "description": "- Mii UNICO IDOLO ES DiOS -//-Mii Liimiite El Ciielo, :) #", "url": "https://t.co/APZ8IQNq3T", "entities": {"url": {"urls": [{"url": "https://t.co/APZ8IQNq3T", "expanded_url": "https://www.facebook.com/fknmaicol.araujo", "display_url": "facebook.com/fknmaicol.arau\u2026", "indices": [0, 23]}]}, "description": {"urls": []}}, "protected": false, "followers_count": 308, "friends_count": 46, "listed_count": 120, "created_at": "Mon Mar 17 00:43:44 +0000 2014", "favourites_count": 37, "utc_offset": null, "time_zone": null, "geo_enabled": true, "verified": false, "statuses_count": 1164826, "lang": null, "contributors_enabled": false, "is_translator": false, "is_translation_enabled": false, "profile_background_color": "3B94D9", "profile_background_image_url": "http://abs.twimg.com/images/themes/theme1/bg.png", "profile_background_image_url_https": "https://abs.twimg.com/images/themes/theme1/bg.png", "profile_background_tile": true, "profile_image_url": "http://pbs.twimg.com/profile_images/1420707127669178370/4R3GAizD_normal.jpg", "profile_image_url_https": "https://pbs.twimg.com/profile_images/1420707127669178370/4R3GAizD_normal.jpg", "profile_banner_url": "https://pbs.twimg.com/profile_banners/2393490350/1456011969", "profile_link_color": "263236", "profile_sidebar_border_color": "000000", "profile_sidebar_fill_color": "DDEEF6", "profile_text_color": "333333", "profile_use_background_image": true, "has_extended_profile": false, "default_profile": false, "default_profile_image": false, "following": null, "follow_request_sent": null, "notifications": null, "translator_type": "regular", "withheld_in_countries": []}, "geo": null, "coordinates": null, "place": null, "contributors": null, "is_quote_status": false, "retweet_count": 0, "favorite_count": 0, "favorited": false, "retweeted": false, "possibly_sensitive": false, "lang": "en"}