{"created_at": "Wed Nov 28 16:44:44 +0000 2018", "id": 1067821605932347392, "id_str": "1067821605932347392", "text": "@Judy_Cockerton @SpotTheLoon2010 @TheWrestleHub @Sullyvan2_2 @Chris26H @CCuk76 @TheRealCeekay @mike_b8_larrik\u2026 https://t.co/Lco18Zo44n", "truncated": true, "entities": {"hashtags": [], "symbols": [], "user_mentions": [{"screen_name": "Judy_Cockerton", "name": "Judy Cockerton\ud83c\uddfa\ud83c\udde6\ud83d\udd4a", "id": 2358609623, "id_str": "2358609623", "indices": [0, 15]}, {"screen_name": "SpotTheLoon2010", "name": "Dave", "id": 118867974, "id_str": "118867974", "indices": [16, 32]}, {"screen_name": "thewrestlehub", "name": "WrestleHub", "id": 1539379401024053249, "id_str": "1539379401024053249", "indices": [33, 47]}, {"screen_name": "CCuk76", "name": "Chris", "id": 347274888, "id_str": "347274888", "indices": [71, 78]}, {"screen_name": "TheRealCeekay", "name": "Ceekay", "id": 20919567, "id_str": "20919567", "indices": [79, 93]}], "urls": [{"url": "https://t.co/Lco18Zo44n", "expanded_url": "https://twitter.com/i/web/status/1067821605932347392", "display_url": "twitter.com/i/web/status/1\u2026", "indices": [111, 134]}]}, "source": "<a href=\"http://twitter.com\" rel=\"nofollow\">Twitter Web Client</a>", "in_reply_to_status_id": 1067577408818200576, "in_reply_to_status_id_str": "1067577408818200576", "in_reply_to_user_id": 2358609623, "in_reply_to_user_id_str": "2358609623", "in_reply_to_screen_name": "Judy_Cockerton", "user": {"id": 43664342, "id_str": "43664342", "name": "@lordofparis", "screen_name": "lordofparis", "location": "Portsmouth - UK", "description": "Football mad. Arsenal \u26bd PSG \u26bd Nothing is impossible. Never give up and keep on fighting. Retweeting does not mean endorsing.", "url": null, "entities": {"description": {"urls": []}}, "protected": false, "followers_count": 27372, "friends_count": 19861, "listed_count": 80, "created_at": "Sun May 31 08:52:40 +0000 2009", "favourites_count": 85899, "utc_offset": null, "time_zone": null, "geo_enabled": true, "verified": false, "statuses_count": 177134, "lang": null, "contributors_enabled": false, "is_translator": false, "is_translation_enabled": false, "profile_background_color": "9AE4E8", "profile_background_image_url": "http://abs.twimg.com/images/themes/theme15/bg.png", "profile_background_image_url_https": "https://abs.twimg.com/images/themes/theme15/bg.png", "profile_background_tile": true, "profile_image_url": "http://pbs.twimg.com/profile_images/1531940561992749056/j41-O01-_normal.jpg", "profile_image_url_https": "https://pbs.twimg.com/profile_images/1531940561992749056/j41-O01-_normal.jpg", "profile_banner_url": "https://pbs.twimg.com/profile_banners/43664342/1650212327", "profile_link_color": "1B95E0", "profile_sidebar_border_color": "000000", "profile_sidebar_fill_color": "C0DFEC", "profile_text_color": "333333", "profile_use_background_image": true, "has_extended_profile": true, "default_profile": false, "default_profile_image": false, "following": null, "follow_request_sent": null, "notifications": null, "translator_type": "none", "withheld_in_countries": []}, "geo": null, "coordinates": null, "place": null, "contributors": null, "is_quote_status": false, "retweet_count": 0, "favorite_count": 2, "favorited": false, "retweeted": false, "lang": "en"}