{"created_at": "Wed Jul 25 23:13:34 +0000 2018", "id": 1022258586196488192, "id_str": "1022258586196488192", "text": "@rryder13 @jessfedigan @pibblecollector @BananaNunChucks @AmLeUSA @BretBaier @FoxNews @CNN @kaitlancollins You can\u2026 https://t.co/IDBGyUpGhQ", "truncated": true, "entities": {"hashtags": [], "symbols": [], "user_mentions": [{"screen_name": "rryder13", "name": "Ryder23", "id": 2886879235, "id_str": "2886879235", "indices": [0, 9]}, {"screen_name": "pibblecollector", "name": "PibbleCollector\ud83d\udc36", "id": 460086828, "id_str": "460086828", "indices": [23, 39]}, {"screen_name": "BananaNunChucks", "name": "\ud835\udd72\ud835\udd8d\ud835\udd8a\ud835\udd99\ud835\udd99\ud835\udd94 \ud835\udd6e\ud835\udd8d\ud835\udd9a\ud835\udd97\ud835\udd88\ud835\udd8d\ua4d8\ud835\udd94\u042f\ud835\udd93\ud835\udd8a\ud835\udd97", "id": 826240785301504000, "id_str": "826240785301504000", "indices": [40, 56]}, {"screen_name": "BretBaier", "name": "Bret Baier", "id": 18646108, "id_str": "18646108", "indices": [66, 76]}, {"screen_name": "FoxNews", "name": "Fox News", "id": 1367531, "id_str": "1367531", "indices": [77, 85]}, {"screen_name": "CNN", "name": "CNN", "id": 759251, "id_str": "759251", "indices": [86, 90]}, {"screen_name": "kaitlancollins", "name": "Kaitlan Collins", "id": 180107694, "id_str": "180107694", "indices": [91, 106]}], "urls": [{"url": "https://t.co/IDBGyUpGhQ", "expanded_url": "https://twitter.com/i/web/status/1022258586196488192", "display_url": "twitter.com/i/web/status/1\u2026", "indices": [116, 139]}]}, "source": "<a href=\"https://mobile.twitter.com\" rel=\"nofollow\">Twitter Web App</a>", "in_reply_to_status_id": 1022256219061243904, "in_reply_to_status_id_str": "1022256219061243904", "in_reply_to_user_id": 2886879235, "in_reply_to_user_id_str": "2886879235", "in_reply_to_screen_name": "rryder13", "user": {"id": 1713468230, "id_str": "1713468230", "name": "cherokee welch \ud83c\udf35\ud83c\udf0a\ud83c\uddfa\ud83c\uddf8\ud83d\ude0e", "screen_name": "cherokee_welch", "location": "The wild wild west", "description": "Clean&https://t.co/hbfMduASwQ.Politics.Animals.Rock&Blues,Celtic&Country. Dire Straits/Pink Floyd/Johnny Cash&more. #Resist #USAFbrat #Recovery #Vets #AZ#CA#WY", "url": null, "entities": {"description": {"urls": [{"url": "https://t.co/hbfMduASwQ", "expanded_url": "http://sober.FilmNoir.TV", "display_url": "sober.FilmNoir.TV", "indices": [6, 29]}]}}, "protected": false, "followers_count": 3936, "friends_count": 4997, "listed_count": 8, "created_at": "Fri Aug 30 18:47:50 +0000 2013", "favourites_count": 252399, "utc_offset": null, "time_zone": null, "geo_enabled": false, "verified": false, "statuses_count": 129780, "lang": null, "contributors_enabled": false, "is_translator": false, "is_translation_enabled": false, "profile_background_color": "C0DEED", "profile_background_image_url": "http://abs.twimg.com/images/themes/theme1/bg.png", "profile_background_image_url_https": "https://abs.twimg.com/images/themes/theme1/bg.png", "profile_background_tile": false, "profile_image_url": "http://pbs.twimg.com/profile_images/1031477417297072130/4rJoWP9p_normal.jpg", "profile_image_url_https": "https://pbs.twimg.com/profile_images/1031477417297072130/4rJoWP9p_normal.jpg", "profile_banner_url": "https://pbs.twimg.com/profile_banners/1713468230/1530412283", "profile_link_color": "1DA1F2", "profile_sidebar_border_color": "C0DEED", "profile_sidebar_fill_color": "DDEEF6", "profile_text_color": "333333", "profile_use_background_image": true, "has_extended_profile": false, "default_profile": true, "default_profile_image": false, "following": null, "follow_request_sent": null, "notifications": null, "translator_type": "none", "withheld_in_countries": []}, "geo": null, "coordinates": null, "place": null, "contributors": null, "is_quote_status": false, "retweet_count": 0, "favorite_count": 0, "favorited": false, "retweeted": false, "lang": "en"}