{"created_at": "Tue Mar 21 21:28:03 +0000 2017", "id": 844299592099352579, "id_str": "844299592099352579", "text": "Snoop Dogg Arrested For Conspiracy After Talking About His \u2018Murder Trump\u2019 Video - THE LAST DEPLORABLES https://t.co/wEmIODo6rc", "truncated": false, "entities": {"hashtags": [], "symbols": [], "user_mentions": [], "urls": [{"url": "https://t.co/wEmIODo6rc", "expanded_url": "http://fb.me/6sKBEY5gQ", "display_url": "fb.me/6sKBEY5gQ", "indices": [103, 126]}]}, "source": "<a href=\"http://www.facebook.com/twitter\" rel=\"nofollow\">Facebook</a>", "in_reply_to_status_id": null, "in_reply_to_status_id_str": null, "in_reply_to_user_id": null, "in_reply_to_user_id_str": null, "in_reply_to_screen_name": null, "user": {"id": 32315396, "id_str": "32315396", "name": "BriZ BarZ", "screen_name": "BriZBarzBaby", "location": "Ebbets Field", "description": "BriZ Barz im jus a rapper tryna life my life thru music and get the fuck outta poverty and stick a middle finger to oppression all the while", "url": null, "entities": {"description": {"urls": []}}, "protected": false, "followers_count": 163, "friends_count": 320, "listed_count": 0, "created_at": "Fri Apr 17 05:05:38 +0000 2009", "favourites_count": 27, "utc_offset": null, "time_zone": null, "geo_enabled": false, "verified": false, "statuses_count": 13784, "lang": null, "contributors_enabled": false, "is_translator": false, "is_translation_enabled": false, "profile_background_color": "0A0A0A", "profile_background_image_url": "http://abs.twimg.com/images/themes/theme1/bg.png", "profile_background_image_url_https": "https://abs.twimg.com/images/themes/theme1/bg.png", "profile_background_tile": false, "profile_image_url": "http://pbs.twimg.com/profile_images/466783772340281345/WodsWY_g_normal.jpeg", "profile_image_url_https": "https://pbs.twimg.com/profile_images/466783772340281345/WodsWY_g_normal.jpeg", "profile_banner_url": "https://pbs.twimg.com/profile_banners/32315396/1400124804", "profile_link_color": "6219CF", "profile_sidebar_border_color": "000000", "profile_sidebar_fill_color": "DDEEF6", "profile_text_color": "333333", "profile_use_background_image": true, "has_extended_profile": false, "default_profile": false, "default_profile_image": false, "following": null, "follow_request_sent": null, "notifications": null, "translator_type": "none", "withheld_in_countries": []}, "geo": null, "coordinates": null, "place": null, "contributors": null, "is_quote_status": false, "retweet_count": 0, "favorite_count": 0, "favorited": false, "retweeted": false, "possibly_sensitive": false, "lang": "en"}