{"created_at": "Tue Aug 22 13:38:21 +0000 2017", "id": 899989116997251072, "id_str": "899989116997251072", "text": "NASA Confirms Earth Will Experience 15 Days Of Darkness In November 2017 https://t.co/n0rUc36DIF", "truncated": false, "entities": {"hashtags": [], "symbols": [], "user_mentions": [], "urls": [{"url": "https://t.co/n0rUc36DIF", "expanded_url": "http://fb.me/6zQx6NpNe", "display_url": "fb.me/6zQx6NpNe", "indices": [73, 96]}]}, "source": "<a href=\"http://www.facebook.com/twitter\" rel=\"nofollow\">Facebook</a>", "in_reply_to_status_id": null, "in_reply_to_status_id_str": null, "in_reply_to_user_id": null, "in_reply_to_user_id_str": null, "in_reply_to_screen_name": null, "user": {"id": 817274148, "id_str": "817274148", "name": "PAZRealtorPH", "screen_name": "pazmerichel", "location": "cebu city", "description": "sharing my passion in real estate Philippines! proudly affiliated with filipino homes/Leuterio Realty", "url": "https://t.co/BWfe8xM2ws", "entities": {"url": {"urls": [{"url": "https://t.co/BWfe8xM2ws", "expanded_url": "https://phtopinvestment.blogspot.com", "display_url": "phtopinvestment.blogspot.com", "indices": [0, 23]}]}, "description": {"urls": []}}, "protected": false, "followers_count": 26, "friends_count": 87, "listed_count": 1, "created_at": "Tue Sep 11 11:58:00 +0000 2012", "favourites_count": 16, "utc_offset": null, "time_zone": null, "geo_enabled": true, "verified": false, "statuses_count": 6195, "lang": null, "contributors_enabled": false, "is_translator": false, "is_translation_enabled": false, "profile_background_color": "D7E7E6", "profile_background_image_url": "http://abs.twimg.com/images/themes/theme1/bg.png", "profile_background_image_url_https": "https://abs.twimg.com/images/themes/theme1/bg.png", "profile_background_tile": false, "profile_image_url": "http://pbs.twimg.com/profile_images/1123307187990712321/g-ShCGxT_normal.png", "profile_image_url_https": "https://pbs.twimg.com/profile_images/1123307187990712321/g-ShCGxT_normal.png", "profile_banner_url": "https://pbs.twimg.com/profile_banners/817274148/1556652328", "profile_link_color": "856755", "profile_sidebar_border_color": "97B8AB", "profile_sidebar_fill_color": "C1D9D0", "profile_text_color": "C28C77", "profile_use_background_image": true, "has_extended_profile": true, "default_profile": false, "default_profile_image": false, "following": null, "follow_request_sent": null, "notifications": null, "translator_type": "none", "withheld_in_countries": []}, "geo": null, "coordinates": null, "place": null, "contributors": null, "is_quote_status": false, "retweet_count": 0, "favorite_count": 0, "favorited": false, "retweeted": false, "possibly_sensitive": false, "lang": "en"}