{"retweets": [{"created_at": "Fri Jun 29 11:21:27 +0000 2018", "id": 1012657291898904577, "id_str": "1012657291898904577", "text": "RT @SavoySummer: Hey people in OH04! Please vote for Janet Garret for US House of Representatives. She\u2019s running against Jim Jordan. Nuff s\u2026", "truncated": false, "entities": {"hashtags": [], "symbols": [], "user_mentions": [{"screen_name": "SavoySummer", "name": "SavoySummer \ud83c\udf3b\u262e\ufe0f", "id": 15879550, "id_str": "15879550", "indices": [3, 15]}], "urls": []}, "source": "<a href=\"http://twitter.com/download/android\" rel=\"nofollow\">Twitter for Android</a>", "in_reply_to_status_id": null, "in_reply_to_status_id_str": null, "in_reply_to_user_id": null, "in_reply_to_user_id_str": null, "in_reply_to_screen_name": null, "user": {"id": 501397421, "id_str": "501397421", "name": "Beverly Stands with Ukraine \ud83c\udf0a Women's rights", "screen_name": "BeverlyFolkers", "location": "Illinois", "description": "\ud83c\udf0aBan AR -15s  Pro Choice Women's rights are human rights             Freedom for all \n      \n\ud83c\udf0aFBR\ud83c\udf0a   #BlueWave2022\nResist             #LBGTQ\nNo DMs No Lists", "url": null, "entities": {"description": {"urls": []}}, "protected": false, "followers_count": 18411, "friends_count": 17928, "listed_count": 180, "created_at": "Fri Feb 24 03:11:05 +0000 2012", "favourites_count": 292853, "utc_offset": null, "time_zone": null, "geo_enabled": true, "verified": false, "statuses_count": 698671, "lang": null, "contributors_enabled": false, "is_translator": false, "is_translation_enabled": false, "profile_background_color": "FFFFFF", "profile_background_image_url": "http://abs.twimg.com/images/themes/theme1/bg.png", "profile_background_image_url_https": "https://abs.twimg.com/images/themes/theme1/bg.png", "profile_background_tile": true, "profile_image_url": "http://pbs.twimg.com/profile_images/378800000603292063/297d5d7745776d46fc915e309c234d0e_normal.jpeg", "profile_image_url_https": "https://pbs.twimg.com/profile_images/378800000603292063/297d5d7745776d46fc915e309c234d0e_normal.jpeg", "profile_banner_url": "https://pbs.twimg.com/profile_banners/501397421/1658689586", "profile_link_color": "000000", "profile_sidebar_border_color": "FFFFFF", "profile_sidebar_fill_color": "FFFFFF", "profile_text_color": "000000", "profile_use_background_image": true, "has_extended_profile": true, "default_profile": false, "default_profile_image": false, "following": null, "follow_request_sent": null, "notifications": null, "translator_type": "none", "withheld_in_countries": []}, "geo": null, "coordinates": null, "place": null, "contributors": null, "retweeted_status": {"created_at": "Fri Jun 29 10:45:25 +0000 2018", "id": 1012648225310994432, "id_str": "1012648225310994432", "text": "Hey people in OH04! Please vote for Janet Garret for US House of Representatives. She\u2019s running against Jim Jordan.\u2026 https://t.co/GPA9i0QVYp", "truncated": true, "entities": {"hashtags": [], "symbols": [], "user_mentions": [], "urls": [{"url": "https://t.co/GPA9i0QVYp", "expanded_url": "https://twitter.com/i/web/status/1012648225310994432", "display_url": "twitter.com/i/web/status/1\u2026", "indices": [117, 140]}]}, "source": "<a href=\"http://twitter.com/download/iphone\" rel=\"nofollow\">Twitter for iPhone</a>", "in_reply_to_status_id": null, "in_reply_to_status_id_str": null, "in_reply_to_user_id": null, "in_reply_to_user_id_str": null, "in_reply_to_screen_name": null, "user": {"id": 15879550, "id_str": "15879550", "name": "SavoySummer \ud83c\udf3b\u262e\ufe0f", "screen_name": "SavoySummer", "location": "Atlanta, GA", "description": "\ud83c\udf3bProgressive, Tree hugger, Crone. My 2022 midterms mantra: Look up, lean in, have hope and fight like hell. #VoteBlue2022 #StandWithUkraine", "url": null, "entities": {"description": {"urls": []}}, "protected": false, "followers_count": 8222, "friends_count": 8897, "listed_count": 10, "created_at": "Sun Aug 17 04:24:26 +0000 2008", "favourites_count": 670545, "utc_offset": null, "time_zone": null, "geo_enabled": true, "verified": false, "statuses_count": 84163, "lang": null, "contributors_enabled": false, "is_translator": false, "is_translation_enabled": false, "profile_background_color": "000000", "profile_background_image_url": "http://abs.twimg.com/images/themes/theme19/bg.gif", "profile_background_image_url_https": "https://abs.twimg.com/images/themes/theme19/bg.gif", "profile_background_tile": false, "profile_image_url": "http://pbs.twimg.com/profile_images/1499737437031043080/ECT2EGjo_normal.jpg", "profile_image_url_https": "https://pbs.twimg.com/profile_images/1499737437031043080/ECT2EGjo_normal.jpg", "profile_banner_url": "https://pbs.twimg.com/profile_banners/15879550/1645883133", "profile_link_color": "1B95E0", "profile_sidebar_border_color": "000000", "profile_sidebar_fill_color": "000000", "profile_text_color": "000000", "profile_use_background_image": false, "has_extended_profile": false, "default_profile": false, "default_profile_image": false, "following": null, "follow_request_sent": null, "notifications": null, "translator_type": "none", "withheld_in_countries": []}, "geo": null, "coordinates": null, "place": null, "contributors": null, "is_quote_status": true, "quoted_status_id": 1012367978669543424, "quoted_status_id_str": "1012367978669543424", "quoted_status": {"created_at": "Thu Jun 28 16:11:49 +0000 2018", "id": 1012367978669543424, "id_str": "1012367978669543424", "text": "This is Janet Garrett\n\nShe is running against that little prick Jim Jordan in Ohio\u2019s 4th Congressional District\n\nI\u2026 https://t.co/bzwnMvaHuI", "truncated": true, "entities": {"hashtags": [], "symbols": [], "user_mentions": [], "urls": [{"url": "https://t.co/bzwnMvaHuI", "expanded_url": "https://twitter.com/i/web/status/1012367978669543424", "display_url": "twitter.com/i/web/status/1\u2026", "indices": [116, 139]}]}, "source": "<a href=\"http://twitter.com/download/iphone\" rel=\"nofollow\">Twitter for iPhone</a>", "in_reply_to_status_id": null, "in_reply_to_status_id_str": null, "in_reply_to_user_id": null, "in_reply_to_user_id_str": null, "in_reply_to_screen_name": null, "user": {"id": 824320363257413633, "id_str": "824320363257413633", "name": "WTFGOP #RovemberIsComing\ud83c\udf0a", "screen_name": "DogginTrump", "location": "", "description": "Foul-mouth, proud member of the #resistance. If you don\u2019t like the F word then C-ya! This account is not for Republicans, Whiners or Pearl Clutchers.", "url": null, "entities": {"description": {"urls": []}}, "protected": false, "followers_count": 72902, "friends_count": 14647, "listed_count": 201, "created_at": "Wed Jan 25 18:17:44 +0000 2017", "favourites_count": 77169, "utc_offset": null, "time_zone": null, "geo_enabled": false, "verified": false, "statuses_count": 109268, "lang": null, "contributors_enabled": false, "is_translator": false, "is_translation_enabled": false, "profile_background_color": "000000", "profile_background_image_url": "http://abs.twimg.com/images/themes/theme1/bg.png", "profile_background_image_url_https": "https://abs.twimg.com/images/themes/theme1/bg.png", "profile_background_tile": false, "profile_image_url": "http://pbs.twimg.com/profile_images/1060037680409456640/3X9CewKN_normal.jpg", "profile_image_url_https": "https://pbs.twimg.com/profile_images/1060037680409456640/3X9CewKN_normal.jpg", "profile_banner_url": "https://pbs.twimg.com/profile_banners/824320363257413633/1656906988", "profile_link_color": "1B95E0", "profile_sidebar_border_color": "000000", "profile_sidebar_fill_color": "000000", "profile_text_color": "000000", "profile_use_background_image": false, "has_extended_profile": true, "default_profile": false, "default_profile_image": false, "following": null, "follow_request_sent": null, "notifications": null, "translator_type": "none", "withheld_in_countries": []}, "geo": null, "coordinates": null, "place": null, "contributors": null, "is_quote_status": false, "retweet_count": 14870, "favorite_count": 11007, "favorited": false, "retweeted": false, "possibly_sensitive": false, "lang": "en"}, "retweet_count": 3, "favorite_count": 5, "favorited": false, "retweeted": false, "possibly_sensitive": false, "lang": "en"}, "is_quote_status": true, "quoted_status_id": 1012367978669543424, "quoted_status_id_str": "1012367978669543424", "retweet_count": 3, "favorite_count": 0, "favorited": false, "retweeted": false, "lang": "en"}, {"created_at": "Fri Jun 29 11:20:59 +0000 2018", "id": 1012657176928800771, "id_str": "1012657176928800771", "text": "RT @SavoySummer: Hey people in OH04! Please vote for Janet Garret for US House of Representatives. She\u2019s running against Jim Jordan. Nuff s\u2026", "truncated": false, "entities": {"hashtags": [], "symbols": [], "user_mentions": [{"screen_name": "SavoySummer", "name": "SavoySummer \ud83c\udf3b\u262e\ufe0f", "id": 15879550, "id_str": "15879550", "indices": [3, 15]}], "urls": []}, "source": "<a href=\"http://twitter.com/download/iphone\" rel=\"nofollow\">Twitter for iPhone</a>", "in_reply_to_status_id": null, "in_reply_to_status_id_str": null, "in_reply_to_user_id": null, "in_reply_to_user_id_str": null, "in_reply_to_screen_name": null, "user": {"id": 824526829222518785, "id_str": "824526829222518785", "name": "Joe Friday", "screen_name": "packrat1201", "location": "", "description": "I\u2019m voting blue no matter who. Former independent voter turned blue. No lists.", "url": null, "entities": {"description": {"urls": []}}, "protected": false, "followers_count": 3638, "friends_count": 3681, "listed_count": 0, "created_at": "Thu Jan 26 07:58:09 +0000 2017", "favourites_count": 133901, "utc_offset": null, "time_zone": null, "geo_enabled": false, "verified": false, "statuses_count": 143214, "lang": null, "contributors_enabled": false, "is_translator": false, "is_translation_enabled": false, "profile_background_color": "F5F8FA", "profile_background_image_url": null, "profile_background_image_url_https": null, "profile_background_tile": false, "profile_image_url": "http://pbs.twimg.com/profile_images/831535633898283008/ygu2bOy6_normal.jpg", "profile_image_url_https": "https://pbs.twimg.com/profile_images/831535633898283008/ygu2bOy6_normal.jpg", "profile_banner_url": "https://pbs.twimg.com/profile_banners/824526829222518785/1655561471", "profile_link_color": "1DA1F2", "profile_sidebar_border_color": "C0DEED", "profile_sidebar_fill_color": "DDEEF6", "profile_text_color": "333333", "profile_use_background_image": true, "has_extended_profile": false, "default_profile": true, "default_profile_image": false, "following": null, "follow_request_sent": null, "notifications": null, "translator_type": "none", "withheld_in_countries": []}, "geo": null, "coordinates": null, "place": null, "contributors": null, "retweeted_status": {"created_at": "Fri Jun 29 10:45:25 +0000 2018", "id": 1012648225310994432, "id_str": "1012648225310994432", "text": "Hey people in OH04! Please vote for Janet Garret for US House of Representatives. She\u2019s running against Jim Jordan.\u2026 https://t.co/GPA9i0QVYp", "truncated": true, "entities": {"hashtags": [], "symbols": [], "user_mentions": [], "urls": [{"url": "https://t.co/GPA9i0QVYp", "expanded_url": "https://twitter.com/i/web/status/1012648225310994432", "display_url": "twitter.com/i/web/status/1\u2026", "indices": [117, 140]}]}, "source": "<a href=\"http://twitter.com/download/iphone\" rel=\"nofollow\">Twitter for iPhone</a>", "in_reply_to_status_id": null, "in_reply_to_status_id_str": null, "in_reply_to_user_id": null, "in_reply_to_user_id_str": null, "in_reply_to_screen_name": null, "user": {"id": 15879550, "id_str": "15879550", "name": "SavoySummer \ud83c\udf3b\u262e\ufe0f", "screen_name": "SavoySummer", "location": "Atlanta, GA", "description": "\ud83c\udf3bProgressive, Tree hugger, Crone. My 2022 midterms mantra: Look up, lean in, have hope and fight like hell. #VoteBlue2022 #StandWithUkraine", "url": null, "entities": {"description": {"urls": []}}, "protected": false, "followers_count": 8222, "friends_count": 8897, "listed_count": 10, "created_at": "Sun Aug 17 04:24:26 +0000 2008", "favourites_count": 670545, "utc_offset": null, "time_zone": null, "geo_enabled": true, "verified": false, "statuses_count": 84163, "lang": null, "contributors_enabled": false, "is_translator": false, "is_translation_enabled": false, "profile_background_color": "000000", "profile_background_image_url": "http://abs.twimg.com/images/themes/theme19/bg.gif", "profile_background_image_url_https": "https://abs.twimg.com/images/themes/theme19/bg.gif", "profile_background_tile": false, "profile_image_url": "http://pbs.twimg.com/profile_images/1499737437031043080/ECT2EGjo_normal.jpg", "profile_image_url_https": "https://pbs.twimg.com/profile_images/1499737437031043080/ECT2EGjo_normal.jpg", "profile_banner_url": "https://pbs.twimg.com/profile_banners/15879550/1645883133", "profile_link_color": "1B95E0", "profile_sidebar_border_color": "000000", "profile_sidebar_fill_color": "000000", "profile_text_color": "000000", "profile_use_background_image": false, "has_extended_profile": false, "default_profile": false, "default_profile_image": false, "following": null, "follow_request_sent": null, "notifications": null, "translator_type": "none", "withheld_in_countries": []}, "geo": null, "coordinates": null, "place": null, "contributors": null, "is_quote_status": true, "quoted_status_id": 1012367978669543424, "quoted_status_id_str": "1012367978669543424", "quoted_status": {"created_at": "Thu Jun 28 16:11:49 +0000 2018", "id": 1012367978669543424, "id_str": "1012367978669543424", "text": "This is Janet Garrett\n\nShe is running against that little prick Jim Jordan in Ohio\u2019s 4th Congressional District\n\nI\u2026 https://t.co/bzwnMvaHuI", "truncated": true, "entities": {"hashtags": [], "symbols": [], "user_mentions": [], "urls": [{"url": "https://t.co/bzwnMvaHuI", "expanded_url": "https://twitter.com/i/web/status/1012367978669543424", "display_url": "twitter.com/i/web/status/1\u2026", "indices": [116, 139]}]}, "source": "<a href=\"http://twitter.com/download/iphone\" rel=\"nofollow\">Twitter for iPhone</a>", "in_reply_to_status_id": null, "in_reply_to_status_id_str": null, "in_reply_to_user_id": null, "in_reply_to_user_id_str": null, "in_reply_to_screen_name": null, "user": {"id": 824320363257413633, "id_str": "824320363257413633", "name": "WTFGOP #RovemberIsComing\ud83c\udf0a", "screen_name": "DogginTrump", "location": "", "description": "Foul-mouth, proud member of the #resistance. If you don\u2019t like the F word then C-ya! This account is not for Republicans, Whiners or Pearl Clutchers.", "url": null, "entities": {"description": {"urls": []}}, "protected": false, "followers_count": 72902, "friends_count": 14647, "listed_count": 201, "created_at": "Wed Jan 25 18:17:44 +0000 2017", "favourites_count": 77169, "utc_offset": null, "time_zone": null, "geo_enabled": false, "verified": false, "statuses_count": 109268, "lang": null, "contributors_enabled": false, "is_translator": false, "is_translation_enabled": false, "profile_background_color": "000000", "profile_background_image_url": "http://abs.twimg.com/images/themes/theme1/bg.png", "profile_background_image_url_https": "https://abs.twimg.com/images/themes/theme1/bg.png", "profile_background_tile": false, "profile_image_url": "http://pbs.twimg.com/profile_images/1060037680409456640/3X9CewKN_normal.jpg", "profile_image_url_https": "https://pbs.twimg.com/profile_images/1060037680409456640/3X9CewKN_normal.jpg", "profile_banner_url": "https://pbs.twimg.com/profile_banners/824320363257413633/1656906988", "profile_link_color": "1B95E0", "profile_sidebar_border_color": "000000", "profile_sidebar_fill_color": "000000", "profile_text_color": "000000", "profile_use_background_image": false, "has_extended_profile": true, "default_profile": false, "default_profile_image": false, "following": null, "follow_request_sent": null, "notifications": null, "translator_type": "none", "withheld_in_countries": []}, "geo": null, "coordinates": null, "place": null, "contributors": null, "is_quote_status": false, "retweet_count": 14870, "favorite_count": 11007, "favorited": false, "retweeted": false, "possibly_sensitive": false, "lang": "en"}, "retweet_count": 3, "favorite_count": 5, "favorited": false, "retweeted": false, "possibly_sensitive": false, "lang": "en"}, "is_quote_status": true, "quoted_status_id": 1012367978669543424, "quoted_status_id_str": "1012367978669543424", "retweet_count": 3, "favorite_count": 0, "favorited": false, "retweeted": false, "lang": "en"}, {"created_at": "Fri Jun 29 11:05:12 +0000 2018", "id": 1012653204604145665, "id_str": "1012653204604145665", "text": "RT @SavoySummer: Hey people in OH04! Please vote for Janet Garret for US House of Representatives. She\u2019s running against Jim Jordan. Nuff s\u2026", "truncated": false, "entities": {"hashtags": [], "symbols": [], "user_mentions": [{"screen_name": "SavoySummer", "name": "SavoySummer \ud83c\udf3b\u262e\ufe0f", "id": 15879550, "id_str": "15879550", "indices": [3, 15]}], "urls": []}, "source": "<a href=\"http://twitter.com/download/iphone\" rel=\"nofollow\">Twitter for iPhone</a>", "in_reply_to_status_id": null, "in_reply_to_status_id_str": null, "in_reply_to_user_id": null, "in_reply_to_user_id_str": null, "in_reply_to_screen_name": null, "user": {"id": 309106340, "id_str": "309106340", "name": "Lynn", "screen_name": "LRick1960", "location": "Upstate NY", "description": "mom,behavioral health administrative assistant extraordinaire, great cook,slightly humorous, northeast resister.Proud daughter of WWII Navy Vet\ud83c\uddfa\ud83c\uddf8", "url": null, "entities": {"description": {"urls": []}}, "protected": false, "followers_count": 14009, "friends_count": 14728, "listed_count": 82, "created_at": "Wed Jun 01 14:56:29 +0000 2011", "favourites_count": 232519, "utc_offset": null, "time_zone": null, "geo_enabled": true, "verified": false, "statuses_count": 208093, "lang": null, "contributors_enabled": false, "is_translator": false, "is_translation_enabled": false, "profile_background_color": "000000", "profile_background_image_url": "http://abs.twimg.com/images/themes/theme1/bg.png", "profile_background_image_url_https": "https://abs.twimg.com/images/themes/theme1/bg.png", "profile_background_tile": false, "profile_image_url": "http://pbs.twimg.com/profile_images/1046566322056957952/WmfqdXeR_normal.jpg", "profile_image_url_https": "https://pbs.twimg.com/profile_images/1046566322056957952/WmfqdXeR_normal.jpg", "profile_banner_url": "https://pbs.twimg.com/profile_banners/309106340/1507503375", "profile_link_color": "7FDBB6", "profile_sidebar_border_color": "000000", "profile_sidebar_fill_color": "000000", "profile_text_color": "000000", "profile_use_background_image": false, "has_extended_profile": false, "default_profile": false, "default_profile_image": false, "following": null, "follow_request_sent": null, "notifications": null, "translator_type": "none", "withheld_in_countries": []}, "geo": null, "coordinates": null, "place": null, "contributors": null, "retweeted_status": {"created_at": "Fri Jun 29 10:45:25 +0000 2018", "id": 1012648225310994432, "id_str": "1012648225310994432", "text": "Hey people in OH04! Please vote for Janet Garret for US House of Representatives. She\u2019s running against Jim Jordan.\u2026 https://t.co/GPA9i0QVYp", "truncated": true, "entities": {"hashtags": [], "symbols": [], "user_mentions": [], "urls": [{"url": "https://t.co/GPA9i0QVYp", "expanded_url": "https://twitter.com/i/web/status/1012648225310994432", "display_url": "twitter.com/i/web/status/1\u2026", "indices": [117, 140]}]}, "source": "<a href=\"http://twitter.com/download/iphone\" rel=\"nofollow\">Twitter for iPhone</a>", "in_reply_to_status_id": null, "in_reply_to_status_id_str": null, "in_reply_to_user_id": null, "in_reply_to_user_id_str": null, "in_reply_to_screen_name": null, "user": {"id": 15879550, "id_str": "15879550", "name": "SavoySummer \ud83c\udf3b\u262e\ufe0f", "screen_name": "SavoySummer", "location": "Atlanta, GA", "description": "\ud83c\udf3bProgressive, Tree hugger, Crone. My 2022 midterms mantra: Look up, lean in, have hope and fight like hell. #VoteBlue2022 #StandWithUkraine", "url": null, "entities": {"description": {"urls": []}}, "protected": false, "followers_count": 8222, "friends_count": 8897, "listed_count": 10, "created_at": "Sun Aug 17 04:24:26 +0000 2008", "favourites_count": 670545, "utc_offset": null, "time_zone": null, "geo_enabled": true, "verified": false, "statuses_count": 84163, "lang": null, "contributors_enabled": false, "is_translator": false, "is_translation_enabled": false, "profile_background_color": "000000", "profile_background_image_url": "http://abs.twimg.com/images/themes/theme19/bg.gif", "profile_background_image_url_https": "https://abs.twimg.com/images/themes/theme19/bg.gif", "profile_background_tile": false, "profile_image_url": "http://pbs.twimg.com/profile_images/1499737437031043080/ECT2EGjo_normal.jpg", "profile_image_url_https": "https://pbs.twimg.com/profile_images/1499737437031043080/ECT2EGjo_normal.jpg", "profile_banner_url": "https://pbs.twimg.com/profile_banners/15879550/1645883133", "profile_link_color": "1B95E0", "profile_sidebar_border_color": "000000", "profile_sidebar_fill_color": "000000", "profile_text_color": "000000", "profile_use_background_image": false, "has_extended_profile": false, "default_profile": false, "default_profile_image": false, "following": null, "follow_request_sent": null, "notifications": null, "translator_type": "none", "withheld_in_countries": []}, "geo": null, "coordinates": null, "place": null, "contributors": null, "is_quote_status": true, "quoted_status_id": 1012367978669543424, "quoted_status_id_str": "1012367978669543424", "quoted_status": {"created_at": "Thu Jun 28 16:11:49 +0000 2018", "id": 1012367978669543424, "id_str": "1012367978669543424", "text": "This is Janet Garrett\n\nShe is running against that little prick Jim Jordan in Ohio\u2019s 4th Congressional District\n\nI\u2026 https://t.co/bzwnMvaHuI", "truncated": true, "entities": {"hashtags": [], "symbols": [], "user_mentions": [], "urls": [{"url": "https://t.co/bzwnMvaHuI", "expanded_url": "https://twitter.com/i/web/status/1012367978669543424", "display_url": "twitter.com/i/web/status/1\u2026", "indices": [116, 139]}]}, "source": "<a href=\"http://twitter.com/download/iphone\" rel=\"nofollow\">Twitter for iPhone</a>", "in_reply_to_status_id": null, "in_reply_to_status_id_str": null, "in_reply_to_user_id": null, "in_reply_to_user_id_str": null, "in_reply_to_screen_name": null, "user": {"id": 824320363257413633, "id_str": "824320363257413633", "name": "WTFGOP #RovemberIsComing\ud83c\udf0a", "screen_name": "DogginTrump", "location": "", "description": "Foul-mouth, proud member of the #resistance. If you don\u2019t like the F word then C-ya! This account is not for Republicans, Whiners or Pearl Clutchers.", "url": null, "entities": {"description": {"urls": []}}, "protected": false, "followers_count": 72902, "friends_count": 14647, "listed_count": 201, "created_at": "Wed Jan 25 18:17:44 +0000 2017", "favourites_count": 77169, "utc_offset": null, "time_zone": null, "geo_enabled": false, "verified": false, "statuses_count": 109268, "lang": null, "contributors_enabled": false, "is_translator": false, "is_translation_enabled": false, "profile_background_color": "000000", "profile_background_image_url": "http://abs.twimg.com/images/themes/theme1/bg.png", "profile_background_image_url_https": "https://abs.twimg.com/images/themes/theme1/bg.png", "profile_background_tile": false, "profile_image_url": "http://pbs.twimg.com/profile_images/1060037680409456640/3X9CewKN_normal.jpg", "profile_image_url_https": "https://pbs.twimg.com/profile_images/1060037680409456640/3X9CewKN_normal.jpg", "profile_banner_url": "https://pbs.twimg.com/profile_banners/824320363257413633/1656906988", "profile_link_color": "1B95E0", "profile_sidebar_border_color": "000000", "profile_sidebar_fill_color": "000000", "profile_text_color": "000000", "profile_use_background_image": false, "has_extended_profile": true, "default_profile": false, "default_profile_image": false, "following": null, "follow_request_sent": null, "notifications": null, "translator_type": "none", "withheld_in_countries": []}, "geo": null, "coordinates": null, "place": null, "contributors": null, "is_quote_status": false, "retweet_count": 14870, "favorite_count": 11007, "favorited": false, "retweeted": false, "possibly_sensitive": false, "lang": "en"}, "retweet_count": 3, "favorite_count": 5, "favorited": false, "retweeted": false, "possibly_sensitive": false, "lang": "en"}, "is_quote_status": true, "quoted_status_id": 1012367978669543424, "quoted_status_id_str": "1012367978669543424", "retweet_count": 3, "favorite_count": 0, "favorited": false, "retweeted": false, "lang": "en"}]}