{"created_at": "Tue Apr 10 17:21:44 +0000 2018", "id": 983756932203806722, "id_str": "983756932203806722", "text": "Red Crescent Says No Evidence of Chemical Attack in Syria\u2019s Douma -  https://t.co/vHhDfW8BSS", "truncated": false, "entities": {"hashtags": [], "symbols": [], "user_mentions": [], "urls": [{"url": "https://t.co/vHhDfW8BSS", "expanded_url": "https://news.antiwar.com/2018/04/09/red-crescent-says-no-evidence-of-chemical-attack-in-syrias-douma/", "display_url": "news.antiwar.com/2018/04/09/red\u2026", "indices": [69, 92]}]}, "source": "<a href=\"http://twitter.com/download/iphone\" rel=\"nofollow\">Twitter for iPhone</a>", "in_reply_to_status_id": null, "in_reply_to_status_id_str": null, "in_reply_to_user_id": null, "in_reply_to_user_id_str": null, "in_reply_to_screen_name": null, "user": {"id": 1355703260, "id_str": "1355703260", "name": "Charlie riggs", "screen_name": "RiggsCharlie", "location": "", "description": "", "url": null, "entities": {"description": {"urls": []}}, "protected": false, "followers_count": 54, "friends_count": 170, "listed_count": 0, "created_at": "Tue Apr 16 00:48:07 +0000 2013", "favourites_count": 5524, "utc_offset": null, "time_zone": null, "geo_enabled": true, "verified": false, "statuses_count": 4490, "lang": null, "contributors_enabled": false, "is_translator": false, "is_translation_enabled": false, "profile_background_color": "C0DEED", "profile_background_image_url": "http://abs.twimg.com/images/themes/theme1/bg.png", "profile_background_image_url_https": "https://abs.twimg.com/images/themes/theme1/bg.png", "profile_background_tile": false, "profile_image_url": "http://pbs.twimg.com/profile_images/3528628231/bd4b026f34ce05e0b9b770a59d9251d1_normal.jpeg", "profile_image_url_https": "https://pbs.twimg.com/profile_images/3528628231/bd4b026f34ce05e0b9b770a59d9251d1_normal.jpeg", "profile_link_color": "1DA1F2", "profile_sidebar_border_color": "C0DEED", "profile_sidebar_fill_color": "DDEEF6", "profile_text_color": "333333", "profile_use_background_image": true, "has_extended_profile": false, "default_profile": true, "default_profile_image": false, "following": null, "follow_request_sent": null, "notifications": null, "translator_type": "none", "withheld_in_countries": []}, "geo": null, "coordinates": null, "place": {"id": "3f5897b87d2bf56c", "url": "https://api.twitter.com/1.1/geo/id/3f5897b87d2bf56c.json", "place_type": "admin", "name": "Delaware", "full_name": "Delaware, USA", "country_code": "US", "country": "United States", "contained_within": [], "bounding_box": {"type": "Polygon", "coordinates": [[[-75.7887564, 38.4510398], [-74.984165, 38.4510398], [-74.984165, 39.839007], [-75.7887564, 39.839007]]]}, "attributes": {}}, "contributors": null, "is_quote_status": false, "retweet_count": 0, "favorite_count": 0, "favorited": false, "retweeted": false, "possibly_sensitive": false, "lang": "en"}