{"created_at": "Thu Dec 08 18:05:53 +0000 2011", "id": 144840134246936576, "id_str": "144840134246936576", "text": "Results of the 2011 National Assessment of Educational Progress are in: City Schools Gain in Reading, Math http://t.co/7ym2tr4c", "truncated": false, "entities": {"hashtags": [], "symbols": [], "user_mentions": [], "urls": [{"url": "http://t.co/7ym2tr4c", "expanded_url": "http://ow.ly/7TbhS", "display_url": "ow.ly/7TbhS", "indices": [107, 127]}]}, "source": "<a href=\"http://www.hootsuite.com\" rel=\"nofollow\">Hootsuite</a>", "in_reply_to_status_id": null, "in_reply_to_status_id_str": null, "in_reply_to_user_id": null, "in_reply_to_user_id_str": null, "in_reply_to_screen_name": null, "user": {"id": 221856643, "id_str": "221856643", "name": "Get Lit! Festival", "screen_name": "GetLitPrograms", "location": "Spokane, WA", "description": "Get Lit! celebrates the written word. Join us for our 25th anniversary festival April 20-23,2023. Virtual events from 2021/2022 are still available via YouTube.", "url": "https://t.co/64qNf43J7U", "entities": {"url": {"urls": [{"url": "https://t.co/64qNf43J7U", "expanded_url": "http://www.getlitfestival.org", "display_url": "getlitfestival.org", "indices": [0, 23]}]}, "description": {"urls": []}}, "protected": false, "followers_count": 1602, "friends_count": 1078, "listed_count": 44, "created_at": "Wed Dec 01 20:17:38 +0000 2010", "favourites_count": 804, "utc_offset": null, "time_zone": null, "geo_enabled": true, "verified": false, "statuses_count": 2360, "lang": null, "contributors_enabled": false, "is_translator": false, "is_translation_enabled": false, "profile_background_color": "000000", "profile_background_image_url": "http://abs.twimg.com/images/themes/theme18/bg.gif", "profile_background_image_url_https": "https://abs.twimg.com/images/themes/theme18/bg.gif", "profile_background_tile": false, "profile_image_url": "http://pbs.twimg.com/profile_images/1481348285159800834/Lnb8Ye2Y_normal.jpg", "profile_image_url_https": "https://pbs.twimg.com/profile_images/1481348285159800834/Lnb8Ye2Y_normal.jpg", "profile_banner_url": "https://pbs.twimg.com/profile_banners/221856643/1642102142", "profile_link_color": "FAB81E", "profile_sidebar_border_color": "000000", "profile_sidebar_fill_color": "000000", "profile_text_color": "000000", "profile_use_background_image": false, "has_extended_profile": true, "default_profile": false, "default_profile_image": false, "following": null, "follow_request_sent": null, "notifications": null, "translator_type": "none", "withheld_in_countries": []}, "geo": null, "coordinates": null, "place": null, "contributors": null, "is_quote_status": false, "retweet_count": 0, "favorite_count": 0, "favorited": false, "retweeted": false, "possibly_sensitive": false, "lang": "en"}