{"created_at": "Tue Jul 19 00:45:31 +0000 2016", "id": 755201869123694592, "id_str": "755201869123694592", "text": "Check out the 2016 Trustees report on Social Security and Medicare premiums! https://t.co/SJxGSRMVLg", "truncated": false, "entities": {"hashtags": [], "symbols": [], "user_mentions": [], "urls": [{"url": "https://t.co/SJxGSRMVLg", "expanded_url": "http://www.forefieldkt.com/kt/trns.aspx?lf=p0&ca=y&xd=062816CASSREPORT", "display_url": "forefieldkt.com/kt/trns.aspx?l\u2026", "indices": [77, 100]}]}, "source": "<a href=\"http://hearsaysystems.com\" rel=\"nofollow\">Hearsay Social</a>", "in_reply_to_status_id": null, "in_reply_to_status_id_str": null, "in_reply_to_user_id": null, "in_reply_to_user_id_str": null, "in_reply_to_screen_name": null, "user": {"id": 3167866687, "id_str": "3167866687", "name": "Pacific Capital RG", "screen_name": "PacCapRG", "location": "Bellevue, WA", "description": "Financial services firm serving business owners, professionals & families. Visit https://t.co/mDOzS3SLgn for contact information and full disclosures.", "url": "https://t.co/knj8cOQviy", "entities": {"url": {"urls": [{"url": "https://t.co/knj8cOQviy", "expanded_url": "http://www.pcrg.com", "display_url": "pcrg.com", "indices": [0, 23]}]}, "description": {"urls": [{"url": "https://t.co/mDOzS3SLgn", "expanded_url": "http://pcrg.com", "display_url": "pcrg.com", "indices": [81, 104]}]}}, "protected": false, "followers_count": 21, "friends_count": 22, "listed_count": 5, "created_at": "Wed Apr 22 19:33:01 +0000 2015", "favourites_count": 4, "utc_offset": null, "time_zone": null, "geo_enabled": false, "verified": false, "statuses_count": 524, "lang": null, "contributors_enabled": false, "is_translator": false, "is_translation_enabled": false, "profile_background_color": "000000", "profile_background_image_url": "http://abs.twimg.com/images/themes/theme1/bg.png", "profile_background_image_url_https": "https://abs.twimg.com/images/themes/theme1/bg.png", "profile_background_tile": false, "profile_image_url": "http://pbs.twimg.com/profile_images/590962484560863232/oWdzabN7_normal.jpg", "profile_image_url_https": "https://pbs.twimg.com/profile_images/590962484560863232/oWdzabN7_normal.jpg", "profile_banner_url": "https://pbs.twimg.com/profile_banners/3167866687/1429732229", "profile_link_color": "0084B4", "profile_sidebar_border_color": "000000", "profile_sidebar_fill_color": "000000", "profile_text_color": "000000", "profile_use_background_image": false, "has_extended_profile": true, "default_profile": false, "default_profile_image": false, "following": null, "follow_request_sent": null, "notifications": null, "translator_type": "none", "withheld_in_countries": []}, "geo": null, "coordinates": null, "place": null, "contributors": null, "is_quote_status": false, "retweet_count": 0, "favorite_count": 0, "favorited": false, "retweeted": false, "possibly_sensitive": false, "lang": "en"}