{"created_at": "Tue Nov 13 16:58:59 +0000 2018", "id": 1062389375009521665, "id_str": "1062389375009521665", "text": "@sincespacies first State of the Union hits the U.S., then UK gets Flamefamm Plus, now you have your channel briefi\u2026 https://t.co/wncQwWpow3", "truncated": true, "entities": {"hashtags": [], "symbols": [], "user_mentions": [{"screen_name": "sincespacies", "name": "...SINCE SPACIES \u26a0\ufe0f PAX 21 DAYS TO GO!", "id": 733864045669810177, "id_str": "733864045669810177", "indices": [0, 13]}], "urls": [{"url": "https://t.co/wncQwWpow3", "expanded_url": "https://twitter.com/i/web/status/1062389375009521665", "display_url": "twitter.com/i/web/status/1\u2026", "indices": [117, 140]}]}, "source": "<a href=\"https://mobile.twitter.com\" rel=\"nofollow\">Mobile Web (M2)</a>", "in_reply_to_status_id": 1060641558687432704, "in_reply_to_status_id_str": "1060641558687432704", "in_reply_to_user_id": 733864045669810177, "in_reply_to_user_id_str": "733864045669810177", "in_reply_to_screen_name": "sincespacies", "user": {"id": 1035913722936606721, "id_str": "1035913722936606721", "name": "\uff77\uff9a\uff91\uffb6\u4e47\uff77\uff91\uffb6\uffb6 \ud83c\udff4\udb40\udc67\udb40\udc62\udb40\udc73\udb40\udc63\udb40\udc74\udb40\udc7f \ud83c\uddfa\ud83c\udde6 \ud83d\udc4d", "screen_name": "Flamefamm", "location": "Glasgow, Scotland", "description": "", "url": "https://t.co/uNrw0orl4T", "entities": {"url": {"urls": [{"url": "https://t.co/uNrw0orl4T", "expanded_url": "https://www.youtube.com/channel/UCqYZBb7cyPt5eUBK5hLcKrg", "display_url": "youtube.com/channel/UCqYZB\u2026", "indices": [0, 23]}]}, "description": {"urls": []}}, "protected": false, "followers_count": 1057, "friends_count": 1202, "listed_count": 3, "created_at": "Sat Sep 01 15:34:12 +0000 2018", "favourites_count": 23316, "utc_offset": null, "time_zone": null, "geo_enabled": true, "verified": false, "statuses_count": 22051, "lang": null, "contributors_enabled": false, "is_translator": false, "is_translation_enabled": false, "profile_background_color": "000000", "profile_background_image_url": "http://abs.twimg.com/images/themes/theme1/bg.png", "profile_background_image_url_https": "https://abs.twimg.com/images/themes/theme1/bg.png", "profile_background_tile": false, "profile_image_url": "http://pbs.twimg.com/profile_images/1379896262674296834/61VtB3Vw_normal.jpg", "profile_image_url_https": "https://pbs.twimg.com/profile_images/1379896262674296834/61VtB3Vw_normal.jpg", "profile_banner_url": "https://pbs.twimg.com/profile_banners/1035913722936606721/1654473822", "profile_link_color": "FF691F", "profile_sidebar_border_color": "000000", "profile_sidebar_fill_color": "000000", "profile_text_color": "000000", "profile_use_background_image": false, "has_extended_profile": true, "default_profile": false, "default_profile_image": false, "following": null, "follow_request_sent": null, "notifications": null, "translator_type": "none", "withheld_in_countries": []}, "geo": null, "coordinates": null, "place": null, "contributors": null, "is_quote_status": false, "retweet_count": 0, "favorite_count": 1, "favorited": false, "retweeted": false, "lang": "en"}