{"created_at": "Tue Jul 31 09:30:08 +0000 2018", "id": 1024225688792920064, "id_str": "1024225688792920064", "text": "\u201dI Have Survived Four Assassination Attempts In Just One Year\u201d \u2013 Dino Melaye https://t.co/7iIS1QNFp9 https://t.co/OhuqjfPrqs", "truncated": false, "entities": {"hashtags": [], "symbols": [], "user_mentions": [], "urls": [{"url": "https://t.co/7iIS1QNFp9", "expanded_url": "http://dlvr.it/QdKrLs", "display_url": "dlvr.it/QdKrLs", "indices": [77, 100]}], "media": [{"id": 1024225685026394112, "id_str": "1024225685026394112", "indices": [101, 124], "media_url": "http://pbs.twimg.com/media/DjbH1X3UUAA3Jok.jpg", "media_url_https": "https://pbs.twimg.com/media/DjbH1X3UUAA3Jok.jpg", "url": "https://t.co/OhuqjfPrqs", "display_url": "pic.twitter.com/OhuqjfPrqs", "expanded_url": "https://twitter.com/chichinwaafrica/status/1024225688792920064/photo/1", "type": "photo", "sizes": {"thumb": {"w": 150, "h": 150, "resize": "crop"}, "medium": {"w": 400, "h": 240, "resize": "fit"}, "small": {"w": 400, "h": 240, "resize": "fit"}, "large": {"w": 400, "h": 240, "resize": "fit"}}}]}, "extended_entities": {"media": [{"id": 1024225685026394112, "id_str": "1024225685026394112", "indices": [101, 124], "media_url": "http://pbs.twimg.com/media/DjbH1X3UUAA3Jok.jpg", "media_url_https": "https://pbs.twimg.com/media/DjbH1X3UUAA3Jok.jpg", "url": "https://t.co/OhuqjfPrqs", "display_url": "pic.twitter.com/OhuqjfPrqs", "expanded_url": "https://twitter.com/chichinwaafrica/status/1024225688792920064/photo/1", "type": "photo", "sizes": {"thumb": {"w": 150, "h": 150, "resize": "crop"}, "medium": {"w": 400, "h": 240, "resize": "fit"}, "small": {"w": 400, "h": 240, "resize": "fit"}, "large": {"w": 400, "h": 240, "resize": "fit"}}}]}, "source": "<a href=\"https://dlvrit.com/\" rel=\"nofollow\">dlvr.it</a>", "in_reply_to_status_id": null, "in_reply_to_status_id_str": null, "in_reply_to_user_id": null, "in_reply_to_user_id_str": null, "in_reply_to_screen_name": null, "user": {"id": 971153246, "id_str": "971153246", "name": "\ud83c\uddf3\ud83c\uddecChi-Chi Nwa' Africa\ud83c\uddf3\ud83c\uddec", "screen_name": "chichinwaafrica", "location": "Phoenix", "description": "", "url": null, "entities": {"description": {"urls": []}}, "protected": false, "followers_count": 8452, "friends_count": 354, "listed_count": 21, "created_at": "Mon Nov 26 02:01:41 +0000 2012", "favourites_count": 48, "utc_offset": null, "time_zone": null, "geo_enabled": true, "verified": false, "statuses_count": 106754, "lang": null, "contributors_enabled": false, "is_translator": false, "is_translation_enabled": false, "profile_background_color": "89C9FA", "profile_background_image_url": "http://abs.twimg.com/images/themes/theme13/bg.gif", "profile_background_image_url_https": "https://abs.twimg.com/images/themes/theme13/bg.gif", "profile_background_tile": true, "profile_image_url": "http://pbs.twimg.com/profile_images/1344846911799398404/zKTGhm9Z_normal.jpg", "profile_image_url_https": "https://pbs.twimg.com/profile_images/1344846911799398404/zKTGhm9Z_normal.jpg", "profile_banner_url": "https://pbs.twimg.com/profile_banners/971153246/1596736363", "profile_link_color": "3B94D9", "profile_sidebar_border_color": "FFFFFF", "profile_sidebar_fill_color": "F6F6F6", "profile_text_color": "333333", "profile_use_background_image": true, "has_extended_profile": false, "default_profile": false, "default_profile_image": false, "following": null, "follow_request_sent": null, "notifications": null, "translator_type": "none", "withheld_in_countries": []}, "geo": null, "coordinates": null, "place": null, "contributors": null, "is_quote_status": false, "retweet_count": 0, "favorite_count": 0, "favorited": false, "retweeted": false, "possibly_sensitive": false, "lang": "en"}